flask_debugtoolbar_djangosql/__init__.py
flask_debugtoolbar_djangosql/panel.py
flask_debugtoolbar_djangosql/templates/panels/django_sql.html
Flask_DebugToolbar_DjangoSQL-0.1.2.dist-info/LICENSE
Flask_DebugToolbar_DjangoSQL-0.1.2.dist-info/METADATA
Flask_DebugToolbar_DjangoSQL-0.1.2.dist-info/WHEEL
Flask_DebugToolbar_DjangoSQL-0.1.2.dist-info/top_level.txt
Flask_DebugToolbar_DjangoSQL-0.1.2.dist-info/RECORD
