Metadata-Version: 2.1
Name: Flask-DebugToolbar-DjangoSQL
Version: 0.1.2
Summary: A Flask Debug Toolbar panel for Django SQL queries.
Home-page: https://github.com/anqiuy/flask_debugtoolbar_djangosql
Author: Joey
Author-email: qiuyu.an@hotmail.com
License: MIT
Platform: UNKNOWN
Classifier: Development Status :: 3 - Alpha
Classifier: Intended Audience :: Developers
Classifier: Programming Language :: Python :: 3
Classifier: License :: OSI Approved :: MIT License
Requires-Dist: Flask
Requires-Dist: Flask-DebugToolbar
Requires-Dist: Django
